{
  "id" : "stg_orders",
  "metainfo" : {
    "label" : "stg_orders",
    "autoLayout" : true,
    "staleState" : "none",
    "sourceSuggestions" : {
      "sources" : [ ]
    },
    "graphConfig" : {
      "userDefinedConfig" : {
        "vars" : { }
      }
    },
    "version" : 3
  },
  "processes" : {
    "source##Xg0snqTo" : {
      "id" : "source##Xg0snqTo",
      "component" : "Seed",
      "metadata" : {
        "label" : "source",
        "phase" : 0,
        "comment" : "-\n    Normally we would select from the table here, but we are using seeds to load\n    our data in this project\n    "
      },
      "properties" : {
        "table" : {
          "name" : "raw_orders",
          "sourceType" : "Seed"
        }
      },
      "ports" : {
        "inputs" : [ ],
        "outputs" : [ {
          "id" : "OxOY9wBz",
          "schema" : {
            "providerType" : "Databricks",
            "fields" : [ {
              "name" : "id",
              "dataType" : {
                "type" : "Integer"
              }
            }, {
              "name" : "user_id",
              "dataType" : {
                "type" : "Integer"
              }
            }, {
              "name" : "order_date",
              "dataType" : {
                "type" : "Date"
              }
            }, {
              "name" : "status",
              "dataType" : {
                "type" : "String"
              }
            } ]
          },
          "slug" : "out"
        } ],
        "isCustomOutputSchema" : false,
        "autoUpdateOnRun" : false
      }
    },
    "renamed##cFRePl5y" : {
      "id" : "renamed##cFRePl5y",
      "component" : "Reformat",
      "metadata" : {
        "label" : "renamed",
        "phase" : 0,
        "macroDependencies" : [ ]
      },
      "properties" : {
        "columnsSelector" : [ "Kyt4Lha7##id", "Kyt4Lha7##user_id", "Kyt4Lha7##order_date", "Kyt4Lha7##status" ],
        "expressions" : [ {
          "expression" : {
            "expression" : "id"
          },
          "alias" : "order_id"
        }, {
          "expression" : {
            "expression" : "user_id"
          },
          "alias" : "customer_id"
        }, {
          "expression" : {
            "expression" : "order_date"
          }
        }, {
          "expression" : {
            "expression" : "status"
          }
        } ]
      },
      "ports" : {
        "inputs" : [ {
          "id" : "Kyt4Lha7",
          "schema" : {
            "providerType" : "Databricks",
            "fields" : [ {
              "name" : "id",
              "dataType" : {
                "type" : "Integer"
              }
            }, {
              "name" : "user_id",
              "dataType" : {
                "type" : "Integer"
              }
            }, {
              "name" : "order_date",
              "dataType" : {
                "type" : "Date"
              }
            }, {
              "name" : "status",
              "dataType" : {
                "type" : "String"
              }
            } ]
          },
          "slug" : "source"
        } ],
        "outputs" : [ {
          "id" : "q7Wx1bjY",
          "slug" : "out"
        } ],
        "isCustomOutputSchema" : false,
        "autoUpdateOnRun" : false
      }
    },
    "stg_orders##kY09lrRI" : {
      "id" : "stg_orders##kY09lrRI",
      "component" : "TargetModel",
      "metadata" : {
        "label" : "stg_orders",
        "phase" : 0,
        "macroDependencies" : [ ]
      },
      "properties" : {
        "customQueryDisabled" : true,
        "customQuery" : false,
        "incrementalEditorDisabled" : true,
        "query" : "SELECT * \n\nFROM renamed\n",
        "incrementalKey" : false,
        "incremental" : {
          "expression" : "true"
        }
      },
      "ports" : {
        "inputs" : [ {
          "id" : "CeY5IXrv",
          "slug" : "renamed"
        } ],
        "outputs" : [ {
          "id" : "kVF8MZku",
          "slug" : "out"
        } ],
        "isCustomOutputSchema" : false,
        "autoUpdateOnRun" : false
      }
    }
  },
  "connections" : [ {
    "id" : "H7OpdTKX",
    "source" : "source##Xg0snqTo",
    "sourcePort" : "OxOY9wBz",
    "target" : "renamed##cFRePl5y",
    "targetPort" : "Kyt4Lha7"
  }, {
    "id" : "syUJUgVK",
    "source" : "renamed##cFRePl5y",
    "sourcePort" : "q7Wx1bjY",
    "target" : "stg_orders##kY09lrRI",
    "targetPort" : "CeY5IXrv"
  } ],
  "component" : "Model"
}